README.md
setup.cfg
setup.py
distributions_adarbha/Binomialdistribution.py
distributions_adarbha/Gaussiandistribution.py
distributions_adarbha/Generaldistribution.py
distributions_adarbha/__init__.py
distributions_adarbha.egg-info/PKG-INFO
distributions_adarbha.egg-info/SOURCES.txt
distributions_adarbha.egg-info/dependency_links.txt
distributions_adarbha.egg-info/not-zip-safe
distributions_adarbha.egg-info/top_level.txt